django_vaultkeeper_adaptor/__init__.py
django_vaultkeeper_adaptor/vaultkeeper_adaptor.py
django_vaultkeeper_adaptor/tests/__init__.py
django_vaultkeeper_adaptor/tests/test_adaptor.py
vaultkeeper_adaptor-0.0.1.dist-info/DESCRIPTION.rst
vaultkeeper_adaptor-0.0.1.dist-info/METADATA
vaultkeeper_adaptor-0.0.1.dist-info/RECORD
vaultkeeper_adaptor-0.0.1.dist-info/WHEEL
vaultkeeper_adaptor-0.0.1.dist-info/metadata.json
vaultkeeper_adaptor-0.0.1.dist-info/top_level.txt
