Metadata-Version: 2.0
Name: vaultkeeper-adaptor
Version: 0.0.1
Summary: A small library that allows Django apps to consume Vaultkeeper output as resource secrets.
Home-page: https://github.com/praekeltfoundation/vaultkeeper
Author: mracter
Author-email: mary@praekelt.org
License: BSD
Platform: UNKNOWN
Requires-Dist: dj-database-url
Provides-Extra: test
Requires-Dist: pytest (>=3.0.0); extra == 'test'
Requires-Dist: responses; extra == 'test'
Requires-Dist: pytest-cov; extra == 'test'
